{
    "Ar36": {
        "error": 0.0010514427689190982,
        "error_type": "SD",
        "filter_outliers_dict": {
            "filter_outliers": true,
            "iterations": 1,
            "std_devs": 2
        },
        "fit": "Parabolic",
        "value": 0.007577239844187003
    },
    "Ar37": {
        "error": 0.05031311199911985,
        "error_type": "SD",
        "filter_outliers_dict": {
            "filter_outliers": true,
            "iterations": 1,
            "std_devs": 2
        },
        "fit": "linear",
        "value": 0.015117348505702169
    },
    "Ar38": {
        "error": 0.08642573479618686,
        "error_type": "SD",
        "filter_outliers_dict": {
            "filter_outliers": true,
            "iterations": 1,
            "std_devs": 2
        },
        "fit": "linear",
        "value": 0.10369169093196698
    },
    "Ar39": {
        "error": 0.05240746399343351,
        "error_type": "SD",
        "filter_outliers_dict": {
            "filter_outliers": true,
            "iterations": 1,
            "std_devs": 2
        },
        "fit": "Parabolic",
        "value": -0.058469469598847815
    },
    "Ar40": {
        "error": 0.042062963118786385,
        "error_type": "SD",
        "filter_outliers_dict": {
            "filter_outliers": true,
            "iterations": 1,
            "std_devs": 2
        },
        "fit": "Parabolic",
        "value": 2.0245281010759846
    },
    "Ar41": {
        "error": 0.10567280359077427,
        "error_type": "SD",
        "filter_outliers_dict": {
            "filter_outliers": true,
            "iterations": 1,
            "std_devs": 2
        },
        "fit": "linear",
        "value": -0.16435752184934022
    }
}